pelidoc/__init__.py
pelidoc/conf.py
pelidoc/theme/AUTHORS.md
pelidoc/theme/LICENSE
pelidoc/theme/README.md
pelidoc/theme/static/css/bootstrap.cerulean.min.css
pelidoc/theme/static/css/bootstrap.cosmo.min.css
pelidoc/theme/static/css/bootstrap.cupid.min.css
pelidoc/theme/static/css/bootstrap.custom.min.css
pelidoc/theme/static/css/bootstrap.cyborg.min.css
pelidoc/theme/static/css/bootstrap.darkly.min.css
pelidoc/theme/static/css/bootstrap.flatly.min.css
pelidoc/theme/static/css/bootstrap.journal.min.css
pelidoc/theme/static/css/bootstrap.lumen.min.css
pelidoc/theme/static/css/bootstrap.min.css
pelidoc/theme/static/css/bootstrap.paper.min.css
pelidoc/theme/static/css/bootstrap.readable-old.min.css
pelidoc/theme/static/css/bootstrap.readable.min.css
pelidoc/theme/static/css/bootstrap.sandstone.min.css
pelidoc/theme/static/css/bootstrap.shamrock.min.css
pelidoc/theme/static/css/bootstrap.simplex.min.css
pelidoc/theme/static/css/bootstrap.slate.min.css
pelidoc/theme/static/css/bootstrap.spacelab.min.css
pelidoc/theme/static/css/bootstrap.superhero.min.css
pelidoc/theme/static/css/bootstrap.united.min.css
pelidoc/theme/static/css/bootstrap.yeti.min.css
pelidoc/theme/static/css/font-awesome.css
pelidoc/theme/static/css/font-awesome.css.map
pelidoc/theme/static/css/font-awesome.min.css
pelidoc/theme/static/css/html4css1.css
pelidoc/theme/static/css/style.css
pelidoc/theme/static/css/typogrify.css
pelidoc/theme/static/css/pygments/autumn.css
pelidoc/theme/static/css/pygments/borland.css
pelidoc/theme/static/css/pygments/bw.css
pelidoc/theme/static/css/pygments/colorful.css
pelidoc/theme/static/css/pygments/default.css
pelidoc/theme/static/css/pygments/emacs.css
pelidoc/theme/static/css/pygments/friendly.css
pelidoc/theme/static/css/pygments/fruity.css
pelidoc/theme/static/css/pygments/github.css
pelidoc/theme/static/css/pygments/igor.css
pelidoc/theme/static/css/pygments/manni.css
pelidoc/theme/static/css/pygments/monokai.css
pelidoc/theme/static/css/pygments/murphy.css
pelidoc-0.0.5.dist-info/METADATA
pelidoc-0.0.5.dist-info/WHEEL
pelidoc-0.0.5.dist-info/entry_points.txt
pelidoc-0.0.5.dist-info/top_level.txt
pelidoc-0.0.5.dist-info/RECORD
